Metadata-Version: 2.1
Name: termkeymonitor
Version: 1.4.5
Summary: Display pressed keys in the terminal
Home-page: https://gitlab.com/nobodyinperson/termkeymonitor
Author: Yann Buechau
Author-email: nobodyinperson@posteo.de
License: GPLv3
Keywords: cli
Classifier: License :: OSI Approved :: GNU General Public License v3 (GPLv3)
Classifier: Programming Language :: Python
Requires-Python: >=3.8
Provides-Extra: textual
